Html5Specification/README.md
Html5Specification/__init__.py
Html5Specification/__main__.py
Html5Specification/file.epub
Html5Specification/index.html
Html5Specification/css/__init__.py
Html5Specification/css/annotations.css
Html5Specification/css/main.css
Html5Specification/css/normalize.css
Html5Specification/css/popup.css
Html5Specification/font/__init__.py
Html5Specification/font/fontello.eot
Html5Specification/font/fontello.svg
Html5Specification/font/fontello.ttf
Html5Specification/font/fontello.woff
Html5Specification/img/__init__.py
Html5Specification/img/annotator-glyph-sprite.png
Html5Specification/img/annotator-icon-sprite.png
Html5Specification/img/apple-touch-icon.png
Html5Specification/img/cancelfullscreen.png
Html5Specification/img/close.png
Html5Specification/img/fullscreen.png
Html5Specification/img/loader.gif
Html5Specification/img/menu-icon.png
Html5Specification/img/save.png
Html5Specification/img/saved.png
Html5Specification/img/settings-s.png
Html5Specification/img/settings.png
Html5Specification/img/star.png
Html5Specification/js/__init__.py
Html5Specification/js/epub.js
Html5Specification/js/epub.min.js
Html5Specification/js/epub.min.map
Html5Specification/js/hooks.min.js
Html5Specification/js/hooks.min.map
Html5Specification/js/reader.js
Html5Specification/js/reader.js.map
Html5Specification/js/reader.min.js
Html5Specification/js/reader.min.map
Html5Specification/js/hooks/__init__.py
Html5Specification/js/hooks/extensions/__init__.py
Html5Specification/js/hooks/extensions/highlight.js
Html5Specification/js/libs/__init__.py
Html5Specification/js/libs/jquery.min.js
Html5Specification/js/libs/localforage.min.js
Html5Specification/js/libs/screenfull.js
Html5Specification/js/libs/screenfull.min.js
Html5Specification/js/libs/zip.min.js
Html5Specification/js/plugins/__init__.py
Html5Specification/js/plugins/hypothesis.js
Html5Specification/js/plugins/search.js
html5_specification-2024.3.2.0.dist-info/METADATA
html5_specification-2024.3.2.0.dist-info/WHEEL
html5_specification-2024.3.2.0.dist-info/entry_points.txt
html5_specification-2024.3.2.0.dist-info/top_level.txt
html5_specification-2024.3.2.0.dist-info/RECORD
